pyncette/__init__.py
pyncette/dynamodb.py
pyncette/errors.py
pyncette/executor.py
pyncette/healthcheck.py
pyncette/model.py
pyncette/mongodb.py
pyncette/mysql.py
pyncette/postgres.py
pyncette/prometheus.py
pyncette/py.typed
pyncette/pyncette.py
pyncette/repository.py
pyncette/sqlite.py
pyncette/task.py
pyncette/utils.py
pyncette/redis/__init__.py
pyncette/redis/list_dynamic.lua
pyncette/redis/manage.lua
pyncette/redis/poll_dynamic.lua
pyncette-1.1.0.dist-info/METADATA
pyncette-1.1.0.dist-info/WHEEL
pyncette-1.1.0.dist-info/licenses/LICENSE
pyncette-1.1.0.dist-info/RECORD
