Metadata-Version: 2.4
Name: pyncette
Version: 1.1.0
Summary: A reliable distributed scheduler with pluggable storage backends
Project-URL: Documentation, https://tibordp.github.io/pyncette/
Project-URL: Changelog, https://tibordp.github.io/pyncette/changelog/
Project-URL: Issue Tracker, https://github.com/tibordp/pyncette/issues
Project-URL: Homepage, https://github.com/tibordp/pyncette
Author-email: Tibor Djurica Potpara <tibor.djurica@ojdip.net>
License: MIT
License-File: LICENSE
Keywords: async,asyncio,cron,distributed,scheduler,task-queue
Classifier: Development Status :: 5 - Production/Stable
Classifier: Intended Audience :: Developers
Classifier: License :: OSI Approved :: MIT License
Classifier: Operating System :: Microsoft :: Windows
Classifier: Operating System :: POSIX
Classifier: Operating System :: Unix
Classifier: Programming Language :: Python
Classifier: Programming Language :: Python :: 3.9
Classifier: Programming Language :: Python :: 3.10
Classifier: Programming Language :: Python :: 3.11
Classifier: Programming Language :: Python :: 3.12
Classifier: Programming Language :: Python :: 3.13
Classifier: Programming Language :: Python :: 3.14
Classifier: Programming Language :: Python :: Implementation :: CPython
Classifier: Topic :: Utilities
Requires-Python: >=3.9
Requires-Dist: aiohttp>=3.8.4
Requires-Dist: aiosqlite>=0.19.0
Requires-Dist: coloredlogs
Requires-Dist: croniter>=1.3.14
Requires-Dist: python-dateutil>=2.8.2
Provides-Extra: all
Requires-Dist: aioboto3>=11.1.0; extra == 'all'
Requires-Dist: aiomysql>=0.1.1; extra == 'all'
Requires-Dist: asyncpg>=0.27.0; extra == 'all'
Requires-Dist: cryptography>=40.0.2; extra == 'all'
Requires-Dist: motor>=3.1.1; extra == 'all'
Requires-Dist: prometheus-client>=0.16.0; extra == 'all'
Requires-Dist: redis>=4.5.4; extra == 'all'
Requires-Dist: uvloop>=0.22.1; extra == 'all'
Provides-Extra: dynamodb
Requires-Dist: aioboto3>=11.1.0; extra == 'dynamodb'
Provides-Extra: mongodb
Requires-Dist: motor>=3.1.1; extra == 'mongodb'
Provides-Extra: mysql
Requires-Dist: aiomysql>=0.1.1; extra == 'mysql'
Requires-Dist: cryptography>=40.0.2; extra == 'mysql'
Provides-Extra: postgres
Requires-Dist: asyncpg>=0.27.0; extra == 'postgres'
Provides-Extra: prometheus
Requires-Dist: prometheus-client>=0.16.0; extra == 'prometheus'
Provides-Extra: redis
Requires-Dist: redis>=4.5.4; extra == 'redis'
Provides-Extra: uvloop
Requires-Dist: uvloop>=0.16.0; extra == 'uvloop'
